README.md
setup.py
SmartTranslator/__init__.py
SmartTranslator/smart_translator.py
SmartTranslator.egg-info/PKG-INFO
SmartTranslator.egg-info/SOURCES.txt
SmartTranslator.egg-info/dependency_links.txt
SmartTranslator.egg-info/requires.txt
SmartTranslator.egg-info/top_level.txt