Metadata-Version: 2.1
Name: SmartTranslator
Version: 1.3
Summary: UNKNOWN
Home-page: UNKNOWN
Author: flw
Author-email: flovvi78@gmail.com
License: UNKNOWN
Platform: UNKNOWN
